gyg_reader/__init__.py
gyg_reader/gyg_reader.py
gyg_reader-0.1.1.dist-info/METADATA
gyg_reader-0.1.1.dist-info/RECORD
gyg_reader-0.1.1.dist-info/WHEEL
gyg_reader-0.1.1.dist-info/top_level.txt
