Metadata-Version: 2.1
Name: gyg-reader
Version: 0.1.1
Summary: Retrieve booking details from GetYourGuide orders
Home-page: http://github.com/sknzl/gyg_reader/
Author: Swen Kunzel
Author-email: swenkuenzel@gmail.com
License: MIT
Platform: UNKNOWN
Requires-Dist: requests
Requires-Dist: lxml
